LICENSE
README.md
setup.py
json2html/__init__.py
json2html/__main__.py
json2html/json2html.py
json_to_html.egg-info/PKG-INFO
json_to_html.egg-info/SOURCES.txt
json_to_html.egg-info/dependency_links.txt
json_to_html.egg-info/entry_points.txt
json_to_html.egg-info/top_level.txt