Metadata-Version: 2.1
Name: json-to-html
Version: 1.0.2
Summary: show JSON in HTML
Home-page: https://github.com/walkerever/json2html
Author: Yonghang Wang
Author-email: wyhang@gmail.com
License: Apache 2
Keywords: json2html,html,json
Classifier: License :: OSI Approved :: Apache Software License
License-File: LICENSE
